tq_img_utils/__init__.py
tq_img_utils/basic_image_operation.py
tq_img_utils/bounding_box.py
tq_img_utils/utils/__init__.py
tq_img_utils-0.1.0.post1.dist-info/LICENSE
tq_img_utils-0.1.0.post1.dist-info/METADATA
tq_img_utils-0.1.0.post1.dist-info/WHEEL
tq_img_utils-0.1.0.post1.dist-info/top_level.txt
tq_img_utils-0.1.0.post1.dist-info/RECORD
