Metadata-Version: 2.1
Name: tq_img_utils
Version: 0.1.0.post1
Summary: Some image simple operation.
Home-page: https://gitee.com/torchW/tq_img_utils.git
Author: TripleQuiz
Author-email: triple_quiz@163.com
License: MIT
Keywords: python,util,image operation,opencv,PIL
Classifier: Development Status :: 3 - Alpha
Classifier: License :: OSI Approved :: MIT License
Classifier: Programming Language :: Python :: 3.6
Classifier: Programming Language :: Python :: 3.7
Classifier: Programming Language :: Python :: 3.8
Classifier: Programming Language :: Python :: 3.9
Classifier: Programming Language :: Python :: 3.10
Classifier: Programming Language :: Python :: 3.11
Classifier: Intended Audience :: Developers
Classifier: Operating System :: Microsoft :: Windows
Classifier: Natural Language :: Chinese (Simplified)
Requires-Python: >=3.6, <3.12
License-File: LICENSE
Requires-Dist: numpy>=1.19.3
Requires-Dist: pillow>=8.4.0
Requires-Dist: opencv-python>=4.2.0.32
Requires-Dist: opencv-contrib-python>=4.2.0.32
Requires-Dist: tq-utils>=0.4.0
